devqubit_ui/__init__.py
devqubit_ui/_plugin.py
devqubit_ui/app.py
devqubit_ui/dependencies.py
devqubit_ui/plugins.py
devqubit_ui/py.typed
devqubit_ui/services.py
devqubit_ui/routers/__init__.py
devqubit_ui/routers/api.py
devqubit_ui/static/.gitkeep
devqubit_ui/static/index.html
devqubit_ui/static/assets/index-BGCVZ5av.css
devqubit_ui/static/assets/index-BbbCfgsa.css
devqubit_ui/static/assets/index-BcZMziDM.css
devqubit_ui/static/assets/index-BjxjaPff.js
devqubit_ui/static/assets/index-CPzFDXud.css
devqubit_ui/static/assets/index-CdNzT58h.css
devqubit_ui/static/assets/index-DL6qNW7m.js
devqubit_ui/static/assets/index-DMVhvtRY.js
devqubit_ui/static/assets/index-DPh2EGtA.js
devqubit_ui/static/assets/index-DnVWv6GX.js
devqubit_ui/static/assets/index-Dp7MVVN4.js
devqubit_ui/static/assets/index-LKJS0t1W.js
devqubit_ui/static/assets/index-LMgvsF7G.js
devqubit_ui/static/assets/index-T6HynHcE.css
devqubit_ui/static/assets/index-adHSeyrX.css
devqubit_ui/static/assets/index-eVY7x0ze.css
devqubit_ui-0.1.10.dist-info/METADATA
devqubit_ui-0.1.10.dist-info/WHEEL
devqubit_ui-0.1.10.dist-info/entry_points.txt
devqubit_ui-0.1.10.dist-info/licenses/LICENSE
devqubit_ui-0.1.10.dist-info/RECORD
