Metadata-Version: 2.4
Name: devqubit-ui
Version: 0.1.10
Summary: Web interface for devqubit experiment tracking
Author: devqubit
License-Expression: Apache-2.0
License-File: LICENSE
Keywords: devqubit,experiment-tracking,fastapi,react,web-ui
Classifier: Development Status :: 3 - Alpha
Classifier: Intended Audience :: Developers
Classifier: Intended Audience :: Science/Research
Classifier: License :: OSI Approved :: Apache Software License
Classifier: Programming Language :: Python :: 3
Classifier: Programming Language :: Python :: 3 :: Only
Classifier: Programming Language :: Python :: 3.11
Classifier: Programming Language :: Python :: 3.12
Classifier: Programming Language :: Python :: 3.13
Classifier: Topic :: Scientific/Engineering
Requires-Python: <3.14,>=3.11
Requires-Dist: devqubit-engine<0.2.0,>=0.1.10
Requires-Dist: fastapi>=0.128.0
Requires-Dist: httpx>=0.28.1
Requires-Dist: uvicorn[standard]>=0.40.0
